ytpsync/__init__.py
ytpsync/__main__.py
ytpsync/argumentparser.py
ytpsync/downloader.py
yt_playlist_sync-2024.6.2.3.dist-info/LICENSE
yt_playlist_sync-2024.6.2.3.dist-info/METADATA
yt_playlist_sync-2024.6.2.3.dist-info/WHEEL
yt_playlist_sync-2024.6.2.3.dist-info/entry_points.txt
yt_playlist_sync-2024.6.2.3.dist-info/top_level.txt
yt_playlist_sync-2024.6.2.3.dist-info/RECORD
