Metadata-Version: 2.1
Name: yt-playlist-sync
Version: 2024.6.2.3
Summary: Sync a YouTube playlist to a directory on your system using yt-dlp
Author-email: Willow Ciesialka <wciesialka@gmail.com>
License: GNU GENERAL PUBLIC LICENSE
Project-URL: Homepage, https://pypi.org/project/yt-playlist-sync/
Project-URL: Repository, https://github.com/wciesialka/yt-playlist-sync
Project-URL: Issues, https://github.com/wciesialka/yt-playlist-sync/issues
Keywords: yt-dl,yt-dlp,youtube,music,videos,downloader
Classifier: Development Status :: 4 - Beta
Classifier: Environment :: Console
Classifier: Intended Audience :: End Users/Desktop
Classifier: License :: OSI Approved :: GNU General Public License v3 (GPLv3)
Classifier: Natural Language :: English
Classifier: Operating System :: OS Independent
Classifier: Programming Language :: Python :: 3.10
Classifier: Topic :: System :: Archiving :: Backup
Classifier: Topic :: Internet
Classifier: Topic :: Multimedia :: Sound/Audio
Classifier: Topic :: Multimedia :: Video
Requires-Python: >=3.10
License-File: LICENSE
Requires-Dist: yt-dlp >=2024.5.27
